selection/__init__.py
selection/backend_lxml.py
selection/backend_pyquery.py
selection/base.py
selection/const.py
selection/errors.py
selection/util.py
selection-2.0.1.dist-info/METADATA
selection-2.0.1.dist-info/WHEEL
selection-2.0.1.dist-info/top_level.txt
selection-2.0.1.dist-info/RECORD
